habra_favorites/__init__.py
habra_favorites/exporters.py
habra_favorites/items.py
habra_favorites/loaders.py
habra_favorites/main.py
habra_favorites/pipelines.py
habra_favorites/settings.py
habra_favorites/spiders/__init__.py
habra_favorites/spiders/favorites_spider.py
habra_favorites/templates/base.html
habra_favorites-2.0.1.dist-info/LICENSE
habra_favorites-2.0.1.dist-info/METADATA
habra_favorites-2.0.1.dist-info/WHEEL
habra_favorites-2.0.1.dist-info/entry_points.txt
habra_favorites-2.0.1.dist-info/top_level.txt
habra_favorites-2.0.1.dist-info/RECORD
