Metadata-Version: 2.1
Name: habra-favorites
Version: 2.0.1
Summary: Sort your favorites posts from Habrahabr.ru
Home-page: https://github.com/ykalchevskiy/habra-favorites
Author: Yan Kalchevskiy
Author-email: yan.kalchevskiy@gmail.ru
License: MIT
Keywords: scrapy,habr.com,bookmarks,favorites
Classifier: Development Status :: 5 - Production/Stable
Classifier: Environment :: Console
Classifier: License :: OSI Approved :: MIT License
Classifier: Operating System :: Unix
Classifier: Programming Language :: Python :: 3
Classifier: Topic :: Utilities
License-File: LICENSE
Requires-Dist: scrapy
